<DOC>
<EM CATEG="Pessoa">Álvaro Domingues</EM> participa na conversa 'O urbanismo como resposta aos desafios de transformação da cidade'
<EM CATEG="Data">24 de Janeiro de 2017</EM>, <EM CATEG="Hora">18h00</EM>, <EM CATEG="Localizacao">Porto Innovation Hub</EM>
No próximo dia <EM CATEG="Data">24 de Janeiro de 2017</EM>, às <EM CATEG="Hora">18h00</EM>, no <EM CATEG="Localizacao">Porto Innovation Hub</EM>, vai decorrer a conversa "O urbanismo como resposta aos desafios de transformação da cidade" que contará com a participação de <EM CATEG="Pessoa">Gabriela Vaz Pinheiro</EM>, <EM CATEG="Pessoa">Álvaro Domingues</EM> e <EM CATEG="Pessoa">Manuel Correia Fernandes</EM>, como moderador. A entrada é livre (limitada à lotação do espaço, 50 pessoas). + info portoinnovationhub.pt
</DOC>
