<DOC>
II Curso de Ilustração Científica da <EM CATEG="Organizacao">U.Porto</EM> | <EM CATEG="Localizacao">Biblioteca</EM> <EM CATEG="UnidadeOrganica">FCUP</EM>
16-18 e 23-<EM CATEG="Data">25 Fevereiro 2017</EM>
Ilustração Científica a Preto &amp; Branco | MÓDULO I - IC EM TOM CONTÍNUO: O DESENHO A GRAFITE Local | <EM CATEG="Localizacao">Biblioteca</EM> da <EM CATEG="UnidadeOrganica">Faculdade de Ciências</EM>, <EM CATEG="Localizacao">Campo Alegre, Porto</EM> A <EM CATEG="Organizacao">Universidade do Porto</EM> vai promover, em horário pós-laboral, mais um curso de ilustração científica, desta vez dedicado à ILUSTRAÇÃO A PRETO &amp; BRANCO. Neste contexto, serão organizados quatro módulos alusivos a quatro técnicas diferentes - grafite, carvão, tinta-da-China e _scratchboard_. HORÁRIO PÓS-LABORAL | quintas e sextas das <EM CATEG="Hora">18h</EM> às <EM CATEG="Hora">21h</EM> | sábado entre as <EM CATEG="Hora">9h</EM> e as <EM CATEG="Hora">13h</EM> | Inscrições Aqui Vista lateral de crânio de texugo europeu, <EM CATEG="Pessoa">Francisca Cavaleiro</EM> | Legenda Os <EM CATEG="Organizacao">Cursos de Ilustração Científica da Universidade do Porto</EM> (<EM CATEG="Organizacao">CICUP's</EM>) visam promover o exercício da Ilustração Científica (IC) na <EM CATEG="Organizacao">Universidade do Porto</EM>, e ao mesmo tempo colmatar a falta de oferta formativa na área, na região <EM CATEG="Localizacao">Norte de Portugal</EM>. Dando continuidade a iniciativas anteriores neste mesmo âmbito, os cursos destinam-se a toda a comunidade académica e também ao público em geral, estando pensados de forma a funcionarem de modo independente, pelo que a inscrição não requer a frequência de módulos anteriores. Ainda assim, integram um todo coerente, numa lógica de possibilitar uma aprendizagem continuada na área a quem assim o deseje, dotando os participantes dos conhecimentos e competências essenciais à execução de uma ilustração científica. Participe! Divulgue os seus eventos e projetos | comunica@fc.up.pt
</DOC>
