<DOC>
<EM CATEG="UnidadeOrganica">FEP</EM> assina acordo com a <EM CATEG="Organizacao">Universidade de São Paulo</EM> para o <EM CATEG="Curso">Mestrado em Gestão</EM>
PARCERIA CONSOLIDA A RELAÇÃO DA <EM CATEG="UnidadeOrganica">FEP</EM> COM A MELHOR UNIVERSIDADE DA <EM CATEG="Localizacao">AMÉRICA LATINA</EM> E REFORÇA A INTERNACIONALIZAÇÃO DOS CURSOS DE MESTRADO DA <EM CATEG="UnidadeOrganica">FEP</EM>
A <EM CATEG="UnidadeOrganica">Faculdade de Economia da Universidade do Porto</EM> (<EM CATEG="UnidadeOrganica">FEP</EM>) e a <EM CATEG="UnidadeOrganica">Faculdade de Economia, Administração e Contabilidade da Universidade de São Paulo</EM>, no <EM CATEG="Localizacao">Brasil</EM> (<EM CATEG="UnidadeOrganica">FEA-USP</EM>) estabeleceram um acordo de Reconhecimento Mútuo de Formação para os estudantes dos seus cursos de <EM CATEG="Curso">mestrado em Gestão</EM> (<EM CATEG="Curso">Master in Management</EM> da <EM CATEG="UnidadeOrganica">FEP</EM> e <EM CATEG="Curso">Mestrado em Administração</EM> da <EM CATEG="UnidadeOrganica">FEA-USP</EM>). Os estudantes destes mestrados podem assim, mediante seleção, efetuar dois semestres letivos em <EM CATEG="Localizacao">São Paulo</EM> (estudantes da <EM CATEG="UnidadeOrganica">FEP</EM>) e no <EM CATEG="Localizacao">Porto</EM> (estudantes da <EM CATEG="UnidadeOrganica">FEA-USP</EM>) e ver reconhecida a sua formação pelas duas escolas, caso concluam com sucesso o plano de estudos definido e obtenham aprovação nas provas públicas de defesa da dissertação de mestrado. “A parceria agora estabelecida consolida a relação da <EM CATEG="UnidadeOrganica">FEP</EM> com a melhor universidade da <EM CATEG="Localizacao">América Latina</EM>, de acordo com os principais rankings internacionais, e reforça a internacionalização da <EM CATEG="UnidadeOrganica">FEP</EM> e dos seus cursos de mestrado”, salienta a Subdiretora da <EM CATEG="UnidadeOrganica">FEP</EM>, <EM CATEG="Pessoa">Ana Paula Serra</EM>. A Faculdade tem atualmente seis cursos lecionados em inglês (<EM CATEG="Curso">Mestrado em Economia</EM>, <EM CATEG="Curso">Mestrado em Finanças</EM>, <EM CATEG="Curso">Mestrado em Gestão</EM>, <EM CATEG="Curso">Mestrado em Modelação, Análise de Dados e Sistemas de Apoio à Decisão</EM>, <EM CATEG="Curso">Doutoramento em Economia</EM> e <EM CATEG="Curso">Doutoramento em Gestão</EM>). Além do acordo agora estabelecido com a <EM CATEG="UnidadeOrganica">FEA-USP</EM>, a <EM CATEG="UnidadeOrganica">FEP</EM> tem acordos similares com a <EM CATEG="Organizacao">Kedge Business School</EM> (<EM CATEG="Curso">Mestrado em Gestão</EM>), <EM CATEG="Organizacao">Kozminski University</EM> (<EM CATEG="Curso">Mestrado em Finanças</EM>) e <EM CATEG="Organizacao">Universidade de Milão</EM> (<EM CATEG="Curso">Doutoramento em Economia</EM>)." <EM CATEG="Curso">Master in Management</EM> da <EM CATEG="UnidadeOrganica">FEP</EM> O <EM CATEG="Curso">Mestrado em Gestão</EM> é um mestrado de continuidade, full-time , totalmente lecionado em inglês. O curso é dirigido prioritariamente a recém-licenciados em Economia ou Gestão. Os estudantes do <EM CATEG="Curso">Mestrado em Gestão</EM> na <EM CATEG="UnidadeOrganica">FEP</EM> têm a possibilidade de participar no QTEM - Quantitative Techniques for Economics and Management . Este programa, desenvolvido no âmbito de uma rede internacional de <EM CATEG="Curso">mestrados em Economia e Gestão</EM> que integra 19 das mais prestigiadas universidades no mundo, tem como principal propósito o desenvolvimento de competências analíticas e quantitativas de suporte à tomada de decisão num contexto internacional. Veja o vídeo aqui. Mais informações sobre o <EM CATEG="Curso">Master in Management</EM> aqui. <EM CATEG="Curso">Mestrado em Administração</EM> da <EM CATEG="UnidadeOrganica">FEA-USP</EM> O curso tem como público-alvo estudantes recém-licenciados em <EM CATEG="Curso">Gestão</EM>, <EM CATEG="Curso">Economia</EM> ou em áreas similares, fluentes em inglês. O curso visa proporcionar um conhecimento de base sólido nas funções-chave das áreas da gestão e da administração, a par de um conhecimento mais desenvolvido em uma ou varias áreas de especialização (finanças, estratégia e organizações, marketing e comercial, operações e gestão de pessoas). Mais informações sobre o curso aqui.
</DOC>
