<DOC>
Prova de <EM CATEG="Curso">Mestrado em Cuidados Paliativos</EM> | Lic.ª <EM CATEG="Pessoa">Maria Laura Andrade Pereira Ribeiro</EM>
Dia <EM CATEG="Data">2 de fevereiro de 2017</EM> | <EM CATEG="Hora">17.00 horas</EM> | <EM CATEG="Localizacao">Sala de Atos</EM> do <EM CATEG="UnidadeOrganica">Departamento de Ciências Sociais e Saúde</EM> da <EM CATEG="UnidadeOrganica">FMUP</EM>
Dissertação subordinada ao título: “Perceções e Atitudes de Doentes Oncológicos em Cuidados Paliativos e seus Cuidadores relativas à alimentação: uma análise comparativa” Presidente do Júri: <EM CATEG="Pessoa">Rui Manuel Lopes Nunes</EM> - <EM CATEG="UnidadeOrganica">Faculdade de Medicina da Universidade do Porto</EM> Arguente: <EM CATEG="Pessoa">Rosa Sousa Martins da Rocha Begonha</EM> - <EM CATEG="UnidadeOrganica">Faculdade de Ciências da Saúde da Universidade Fernando Pessoa</EM> Cartaz da Prova
</DOC>
